{
  "id": "runner-architecture/aws/aws",
  "title": "AWS Runner Architecture",
  "description": "This page is a placeholder for the planned AWS runner architecture.",
  "source": "@site/docs/runner-architecture/aws/aws.md",
  "sourceDirName": "runner-architecture/aws",
  "slug": "/runner-architecture/aws/",
  "permalink": "/playrunner/docs/runner-architecture/aws/",
  "draft": false,
  "unlisted": false,
  "editUrl": "https://github.com/playrunner/playrunner/tree/main/docs/docs/runner-architecture/aws/aws.md",
  "tags": [],
  "version": "current",
  "sidebarPosition": 3,
  "frontMatter": {
    "sidebar_position": 3,
    "title": "AWS Runner Architecture",
    "sidebar_label": "AWS"
  },
  "sidebar": "tutorialSidebar",
  "previous": {
    "title": "Terraform",
    "permalink": "/playrunner/docs/runner-architecture/gcp/terraform"
  },
  "next": {
    "title": "Azure",
    "permalink": "/playrunner/docs/runner-architecture/azure"
  }
}